opentelemetry/propagators/aws/__init__.py
opentelemetry/propagators/aws/aws_xray_propagator.py
opentelemetry/propagators/aws/version.py
opentelemetry_propagator_aws_xray-1.0.1.dist-info/LICENSE
opentelemetry_propagator_aws_xray-1.0.1.dist-info/METADATA
opentelemetry_propagator_aws_xray-1.0.1.dist-info/WHEEL
opentelemetry_propagator_aws_xray-1.0.1.dist-info/entry_points.txt
opentelemetry_propagator_aws_xray-1.0.1.dist-info/top_level.txt
opentelemetry_propagator_aws_xray-1.0.1.dist-info/RECORD
